prosody/__init__.py
prosody/prosody_api.py
prosody/util.py
prosody/voice_item.py
prosody-0.0.5.dist-info/LICENSE
prosody-0.0.5.dist-info/METADATA
prosody-0.0.5.dist-info/WHEEL
prosody-0.0.5.dist-info/top_level.txt
prosody-0.0.5.dist-info/RECORD
