Metadata-Version: 2.1
Name: prosody
Version: 0.0.5
Summary: Python Prosody API: Emotion & Prosody sensitive TTS
Home-page: UNKNOWN
Author: Yuneui Jeong, Suwon Shin
Author-email: yjeong@humelo.com, ssw0093@humelo.com
License: UNKNOWN
Platform: UNKNOWN
Classifier: Programming Language :: Python :: 3
Classifier: Operating System :: OS Independent
Requires-Dist: aiodns
Requires-Dist: aiohttp
Requires-Dist: cchardet
Requires-Dist: requests
